AUTHORS
INSTALL
LICENSE
MANIFEST.in
README.md
setup.py
django_cherrypy/__init__.py
django_cherrypy.egg-info/PKG-INFO
django_cherrypy.egg-info/SOURCES.txt
django_cherrypy.egg-info/dependency_links.txt
django_cherrypy.egg-info/requires.txt
django_cherrypy.egg-info/top_level.txt
django_cherrypy/management/__init__.py
django_cherrypy/management/commands/__init__.py
django_cherrypy/management/commands/runcpserver.py
django_cherrypy/management/commands/runserver_cp.py