Metadata-Version: 1.0
Name: django-cherrypy
Version: 0.2
Summary: cherrypy, running under django
Home-page: https://github.com/od-eon/django-cherrypy
Author: Calvin Cheng
Author-email: calvin@calvinx.com
License: LICENSE
Platform: UNKNOWN
